tensorneko_util/__init__.py
tensorneko_util/_rich.py
tensorneko_util/version.txt
tensorneko_util/backend/__init__.py
tensorneko_util/backend/audio_lib.py
tensorneko_util/backend/blocking.py
tensorneko_util/backend/parallel.py
tensorneko_util/backend/tqdm.py
tensorneko_util/backend/visual_lib.py
tensorneko_util/debug/__init__.py
tensorneko_util/debug/logger.py
tensorneko_util/debug/parser.py
tensorneko_util/io/__init__.py
tensorneko_util/io/_default_backends.py
tensorneko_util/io/_path_conversion.py
tensorneko_util/io/reader.py
tensorneko_util/io/writer.py
tensorneko_util/io/audio/__init__.py
tensorneko_util/io/audio/audio_data.py
tensorneko_util/io/audio/audio_reader.py
tensorneko_util/io/audio/audio_writer.py
tensorneko_util/io/audio/audio_writer.pyi
tensorneko_util/io/hdf5/__init__.py
tensorneko_util/io/hdf5/hdf5_reader.py
tensorneko_util/io/hdf5/hdf5_writer.py
tensorneko_util/io/image/__init__.py
tensorneko_util/io/image/image_reader.py
tensorneko_util/io/image/image_writer.py
tensorneko_util/io/json/__init__.py
tensorneko_util/io/json/json_data.py
tensorneko_util/io/json/json_reader.py
tensorneko_util/io/json/json_writer.py
tensorneko_util/io/matlab/__init__.py
tensorneko_util/io/matlab/mat_reader.py
tensorneko_util/io/matlab/mat_writer.py
tensorneko_util/io/npy/__init__.py
tensorneko_util/io/npy/npy_reader.py
tensorneko_util/io/npy/npy_writer.py
tensorneko_util/io/pickle/__init__.py
tensorneko_util/io/pickle/pickle_reader.py
tensorneko_util/io/pickle/pickle_writer.py
tensorneko_util/io/text/__init__.py
tensorneko_util/io/text/text_reader.py
tensorneko_util/io/text/text_writer.py
tensorneko_util/io/toml/__init__.py
tensorneko_util/io/toml/toml_reader.py
tensorneko_util/io/toml/toml_writer.py
tensorneko_util/io/video/__init__.py
tensorneko_util/io/video/video_data.py
tensorneko_util/io/video/video_reader.py
tensorneko_util/io/video/video_reader.pyi
tensorneko_util/io/video/video_writer.py
tensorneko_util/io/video/video_writer.pyi
tensorneko_util-0.3.22.dist-info/licenses/LICENSE
tensorneko_util-0.3.22.dist-info/METADATA
tensorneko_util-0.3.22.dist-info/WHEEL
tensorneko_util-0.3.22.dist-info/top_level.txt
tensorneko_util-0.3.22.dist-info/RECORD
