Metadata-Version: 2.4
Name: tensorneko_util
Version: 0.3.22
Summary: The Utils for Library TensorNeko.
Home-page: https://github.com/ControlNet/tensorneko
Author: ControlNet
Author-email: smczx@hotmail.com
Project-URL: Bug Tracker, https://github.com/ControlNet/tensorneko/issues
Project-URL: Source Code, https://github.com/ControlNet/tensorneko
Keywords: deep learning,pytorch,AI,data processing
Classifier: Programming Language :: Python :: 3
Classifier: Programming Language :: Python :: 3.7
Classifier: Programming Language :: Python :: 3.8
Classifier: Programming Language :: Python :: 3.9
Classifier: Programming Language :: Python :: 3.10
Classifier: Programming Language :: Python :: 3.11
Classifier: Programming Language :: Python :: 3.12
Classifier: Programming Language :: Python :: 3.13
Classifier: License :: OSI Approved :: MIT License
Classifier: Operating System :: OS Independent
Classifier: Intended Audience :: Developers
Classifier: Topic :: Scientific/Engineering :: Artificial Intelligence
Classifier: Topic :: Utilities
Requires-Python: >=3.7
License-File: LICENSE
Requires-Dist: numpy>=1.20.1
Requires-Dist: einops>=0.3.0
Dynamic: author
Dynamic: author-email
Dynamic: classifier
Dynamic: description
Dynamic: description-content-type
Dynamic: home-page
Dynamic: keywords
Dynamic: license-file
Dynamic: project-url
Dynamic: requires-dist
Dynamic: requires-python
Dynamic: summary
